scribe/__init__.py
scribe/config.py
scribe/git_utils.py
scribe/model_utils.py
scribe/pr_hook_script.py
scribe/prepare_commit_msg.py
scribe/pull_request_utils.py
scribe/zscribe_cli.py
scribe/cli/__init__.py
scribe/cli/commit.py
scribe/cli/models.py
scribe/cli/pr.py
scribe/cli/utils.py
scribe/cli/hooks/__init__.py
scribe/cli/hooks/install.py
scribe/cli/hooks/remove.py
scribe/cli/hooks/run.py
scribe/cli/hooks/update.py
scribe/plugins/__init__.py
scribe/plugins/anthropic.py
scribe/plugins/base.py
scribe/plugins/bedrock.py
scribe/plugins/ollama.py
scribe/plugins/openai.py
zscribe-0.2.0.dist-info/METADATA
zscribe-0.2.0.dist-info/WHEEL
zscribe-0.2.0.dist-info/entry_points.txt
zscribe-0.2.0.dist-info/top_level.txt
zscribe-0.2.0.dist-info/RECORD
