Metadata-Version: 2.1
Name: zscribe
Version: 0.2.0
Summary: A tool to generate commit messages and pull request descriptions using various AI providers
Home-page: https://github.com/Zithrill/ZScribe
Author: Jake Gribschaw
Author-email: jake@zithrill.io
License: UNKNOWN
Platform: UNKNOWN
Classifier: Development Status :: 3 - Alpha
Classifier: Intended Audience :: Developers
Classifier: License :: OSI Approved :: MIT License
Classifier: Operating System :: OS Independent
Classifier: Programming Language :: Python :: 3
Classifier: Programming Language :: Python :: 3.8
Classifier: Programming Language :: Python :: 3.9
Requires-Python: >=3.8
Requires-Dist: anthropic
Requires-Dist: openai
Requires-Dist: boto3
Requires-Dist: requests
Requires-Dist: click
Requires-Dist: urllib3==1.26.15
Provides-Extra: dev
Requires-Dist: black; extra == "dev"
Requires-Dist: flake8; extra == "dev"
Requires-Dist: pylint; extra == "dev"
Requires-Dist: mypy; extra == "dev"
Requires-Dist: bandit; extra == "dev"
Requires-Dist: types-requests; extra == "dev"
